state_machine/__init__.py
state_machine/exceptions.py
state_machine/state.py
state_machine/state_machine.py
state_machine/states_manager.py
tests/__init__.py
tests/test_state.py
tests/test_state_machine.py
tests/test_states_manager.py
state_machine_designer-0.0.0.dist-info/LICENSE
state_machine_designer-0.0.0.dist-info/METADATA
state_machine_designer-0.0.0.dist-info/WHEEL
state_machine_designer-0.0.0.dist-info/top_level.txt
state_machine_designer-0.0.0.dist-info/RECORD
