Metadata-Version: 2.1
Name: state-machine-designer
Version: 0.0.0
Summary: State machine designer and implementation package
Home-page: https://github.com/Hillerr/state-machine-designer
Author: Hillerr
Author-email: rafaelhiller23@gmail.com
License: UNKNOWN
Download-URL: https://github.com/Hillerr/state-machine-designer/archive/v0.0.0.tar.gz
Platform: UNKNOWN
Classifier: Programming Language :: Python :: 3
Classifier: License :: OSI Approved :: MIT License
Classifier: Operating System :: OS Independent
Requires-Python: >=3.6
